[{"phone":5169385013,"firstName":"Marti","lastName":"Vogt","job_title":"Product Engineer","address":"Fort Lauderdale"},
{"phone":4846329375,"firstName":"Giselle","lastName":"Elecum","job_title":"Assistant Professor","address":"Makariv"},
{"phone":2765499824,"firstName":"Falito","lastName":"Jee","job_title":"Editor","address":"Mbouda"},
{"phone":6086838243,"firstName":"Heda","lastName":"Atcherley","job_title":"Design Engineer","address":"Staroshcherbinovskaya"},
{"phone":6780377107,"firstName":"Liza","lastName":"Edgeler","job_title":"Food Chemist","address":"Troitsk"},
{"phone":8247274196,"firstName":"Malanie","lastName":"Hooks","job_title":"Software Engineer II","address":"Aloleng"},
{"phone":5143916941,"firstName":"Karlene","lastName":"Brent","job_title":"Occupational Therapist","address":"Kaczory"},
{"phone":8270911249,"firstName":"Barton","lastName":"Fordyce","job_title":"Account Representative II","address":"Vitry-le-François"},
{"phone":3512348019,"firstName":"Agneta","lastName":"Ible","job_title":"Chemical Engineer","address":"Gangtun"},
{"phone":1418475899,"firstName":"Morlee","lastName":"Pomeroy","job_title":"Sales Associate","address":"Siuna"},
{"phone":2065753762,"firstName":"Gabriell","lastName":"Govenlock","job_title":"Human Resources Assistant I","address":"Kromy"},
{"phone":3082181359,"firstName":"Dell","lastName":"Duetschens","job_title":"Analog Circuit Design manager","address":"Xinyuan"},
{"phone":8340006322,"firstName":"Lawrence","lastName":"Planke","job_title":"Payment Adjustment Coordinator","address":"Daxin"},
{"phone":6870654953,"firstName":"Aurore","lastName":"Finnis","job_title":"Actuary","address":"Yanmenguan"},
{"phone":8610472809,"firstName":"Coretta","lastName":"Ludovici","job_title":"Product Engineer","address":"Indulang"},
{"phone":8920808720,"firstName":"Annabella","lastName":"Horbath","job_title":"Marketing Assistant","address":"Zeqin"},
{"phone":9190757150,"firstName":"Whitaker","lastName":"Fryer","job_title":"Systems Administrator II","address":"Mulifanua"},
{"phone":4097496869,"firstName":"Eleanore","lastName":"Viant","job_title":"Assistant Professor","address":"Gunung Sugih"},
{"phone":7679051075,"firstName":"Sidnee","lastName":"Sekulla","job_title":"Social Worker","address":"Gunjur Kuta"},
{"phone":2034768096,"firstName":"Tannie","lastName":"Danniel","job_title":"Data Coordiator","address":"Vithkuq"},
{"phone":3338264975,"firstName":"Addi","lastName":"Dyos","job_title":"Administrative Assistant II","address":"Manalongon"},
{"phone":6623259486,"firstName":"Avrit","lastName":"Misson","job_title":"VP Product Management","address":"Shijiazhuang"},
{"phone":5616935227,"firstName":"Keene","lastName":"Humbie","job_title":"Data Coordiator","address":"Jinji"},
{"phone":6259634707,"firstName":"Vanya","lastName":"Willman","job_title":"Product Engineer","address":"Vysočany"},
{"phone":5672218441,"firstName":"Peter","lastName":"Bachs","job_title":"Research Assistant IV","address":"Krasnoarmiys’k"},
{"phone":3191109540,"firstName":"Ruby","lastName":"Kemster","job_title":"Operator","address":"Jianggu"},
{"phone":4874797326,"firstName":"Delmor","lastName":"Filliskirk","job_title":"Assistant Professor","address":"Büzmeýin"},
{"phone":2274118142,"firstName":"Frasquito","lastName":"Beardwell","job_title":"Senior Financial Analyst","address":"Varkaus"},
{"phone":3468217999,"firstName":"Riccardo","lastName":"O'Grady","job_title":"Nuclear Power Engineer","address":"Paris La Défense"},
{"phone":6913219069,"firstName":"Roland","lastName":"Widdowes","job_title":"Help Desk Operator","address":"Guantou"},
{"phone":5959828777,"firstName":"Adan","lastName":"Harty","job_title":"VP Marketing","address":"Corozal"},
{"phone":7991969901,"firstName":"Cherice","lastName":"Mille","job_title":"Human Resources Assistant III","address":"Westonaria"},
{"phone":7814981875,"firstName":"Sue","lastName":"Playden","job_title":"Account Executive","address":"Chenyangzhai"},
{"phone":5272000983,"firstName":"Art","lastName":"Joddens","job_title":"Desktop Support Technician","address":"Witzenhausen"},
{"phone":6722377483,"firstName":"Jone","lastName":"Keefe","job_title":"Information Systems Manager","address":"Katsina"},
{"phone":1946942266,"firstName":"Dusty","lastName":"Hamber","job_title":"Information Systems Manager","address":"Przyborów"},
{"phone":8807148304,"firstName":"Giff","lastName":"Girault","job_title":"General Manager","address":"Del Valle"},
{"phone":8091631918,"firstName":"Lissa","lastName":"Tremathick","job_title":"Help Desk Technician","address":"Águas Formosas"},
{"phone":6229645804,"firstName":"Catrina","lastName":"Horning","job_title":"Payment Adjustment Coordinator","address":"Outeirô"},
{"phone":7624027465,"firstName":"Brandyn","lastName":"Tollow","job_title":"Information Systems Manager","address":"Trompsburg"},
{"phone":2985636721,"firstName":"Lori","lastName":"Browett","job_title":"Structural Engineer","address":"Vaiņode"},
{"phone":1914077874,"firstName":"Jessica","lastName":"Matzkaitis","job_title":"Electrical Engineer","address":"Likupang"},
{"phone":5864826674,"firstName":"Brittani","lastName":"Gegay","job_title":"General Manager","address":"Söderhamn"},
{"phone":5633678454,"firstName":"Aurelea","lastName":"Boltwood","job_title":"Software Consultant","address":"Batu"},
{"phone":3633656393,"firstName":"Camala","lastName":"Healeas","job_title":"Budget/Accounting Analyst II","address":"Pak Phanang"},
{"phone":4112192747,"firstName":"Ange","lastName":"Rapport","job_title":"Senior Sales Associate","address":"Utrecht (stad)"},
{"phone":9198629883,"firstName":"Binnie","lastName":"Esby","job_title":"Clinical Specialist","address":"La Cesira"},
{"phone":7212106325,"firstName":"Datha","lastName":"Duckworth","job_title":"Director of Sales","address":"Ocumare de la Costa"},
{"phone":3543594816,"firstName":"Marty","lastName":"Tattersfield","job_title":"General Manager","address":"Bengras"},
{"phone":9512378687,"firstName":"Eldon","lastName":"Girardet","job_title":"Account Representative II","address":"Podgornaya"},
{"phone":4763040634,"firstName":"Wally","lastName":"Gallear","job_title":"Help Desk Technician","address":"Chamni"},
{"phone":7136617683,"firstName":"Matt","lastName":"Paulucci","job_title":"Help Desk Technician","address":"Jales"},
{"phone":1115587455,"firstName":"Clio","lastName":"Paule","job_title":"Environmental Tech","address":"Guayaquil"},
{"phone":7048596146,"firstName":"Peggie","lastName":"Hempshall","job_title":"Cost Accountant","address":"Manjiang"},
{"phone":5722320880,"firstName":"Estella","lastName":"Ackenson","job_title":"Systems Administrator II","address":"Annecy"},
{"phone":8377849841,"firstName":"Anabella","lastName":"Gethouse","job_title":"Quality Control Specialist","address":"Piracaia"},
{"phone":4281567021,"firstName":"Delores","lastName":"Senecaut","job_title":"Human Resources Manager","address":"Izyum"},
{"phone":5507625831,"firstName":"Stearne","lastName":"Pankethman","job_title":"Editor","address":"Linshe"},
{"phone":5349585664,"firstName":"Alasteir","lastName":"Luttgert","job_title":"Quality Control Specialist","address":"Huangludian"},
{"phone":7421579847,"firstName":"Freddi","lastName":"Dolley","job_title":"Registered Nurse","address":"Bayan Gol"},
{"phone":1863958448,"firstName":"Chloe","lastName":"Bresnahan","job_title":"Help Desk Technician","address":"Dubrovka"},
{"phone":8717623763,"firstName":"Anatol","lastName":"O'Rowane","job_title":"Programmer II","address":"Pavlovka"},
{"phone":1891551622,"firstName":"Horacio","lastName":"Howard - Gater","job_title":"Paralegal","address":"Lincoln"},
{"phone":8766866327,"firstName":"Glyn","lastName":"Turner","job_title":"Information Systems Manager","address":"Nong Saeng"},
{"phone":8624545031,"firstName":"Bridget","lastName":"Braidman","job_title":"Help Desk Operator","address":"Oenam"},
{"phone":9620078268,"firstName":"Darb","lastName":"Ronayne","job_title":"VP Marketing","address":"Vitória"},
{"phone":6180137044,"firstName":"Leslie","lastName":"Duffyn","job_title":"Mechanical Systems Engineer","address":"Lappeenranta"},
{"phone":9087526419,"firstName":"Basile","lastName":"Brabbs","job_title":"Financial Advisor","address":"Campechuela"},
{"phone":2832571126,"firstName":"Norean","lastName":"Tommeo","job_title":"Associate Professor","address":"Golek"},
{"phone":4879401211,"firstName":"Codie","lastName":"Sprade","job_title":"Web Developer I","address":"Roldanillo"},
{"phone":2612702159,"firstName":"Cathrin","lastName":"Elster","job_title":"Software Test Engineer I","address":"Budënnovsk"},
{"phone":8805460867,"firstName":"Karen","lastName":"Horburgh","job_title":"Technical Writer","address":"Qianjin"},
{"phone":1407957634,"firstName":"Konrad","lastName":"Symon","job_title":"Engineer II","address":"Modot"},
{"phone":2876915272,"firstName":"Shawnee","lastName":"Eliesco","job_title":"Account Executive","address":"Santa Bárbara"},
{"phone":9992178657,"firstName":"Gratia","lastName":"Swarbrigg","job_title":"Librarian","address":"Hägersten"},
{"phone":3717316711,"firstName":"Brose","lastName":"Momford","job_title":"Environmental Tech","address":"Miandrarivo"},
{"phone":5638011202,"firstName":"Elga","lastName":"Kanter","job_title":"Food Chemist","address":"Paracambi"},
{"phone":1917688930,"firstName":"Frans","lastName":"Millier","job_title":"Recruiter","address":"Shchastya"},
{"phone":9852134045,"firstName":"Lark","lastName":"Praten","job_title":"Marketing Manager","address":"Utarapasar"},
{"phone":5276923621,"firstName":"Rock","lastName":"Bertolaccini","job_title":"Operator","address":"Santa Catarina Ixtahuacán"},
{"phone":8414748128,"firstName":"Bamby","lastName":"Acott","job_title":"Dental Hygienist","address":"Nuevo Emperador"},
{"phone":1609634770,"firstName":"Letty","lastName":"Batchley","job_title":"Geologist II","address":"Jiangkou"},
{"phone":9321959626,"firstName":"Prescott","lastName":"Lowdiane","job_title":"Speech Pathologist","address":"Tây Hồ"},
{"phone":7525279426,"firstName":"Falkner","lastName":"Thomassin","job_title":"Research Nurse","address":"Jabal os Saraj"},
{"phone":2806687451,"firstName":"Layney","lastName":"Girone","job_title":"Payment Adjustment Coordinator","address":"Takengon"},
{"phone":6695315202,"firstName":"Hirsch","lastName":"Joisce","job_title":"Speech Pathologist","address":"Golbey"},
{"phone":5451285230,"firstName":"Ambrose","lastName":"De Santos","job_title":"Registered Nurse","address":"Stockholm"},
{"phone":9426240327,"firstName":"Lyman","lastName":"Camillo","job_title":"Staff Scientist","address":"Consolacion"},
{"phone":6529108900,"firstName":"Alma","lastName":"Hewertson","job_title":"Research Associate","address":"Hirakata"},
{"phone":6227526418,"firstName":"Marvin","lastName":"Boleyn","job_title":"Associate Professor","address":"Shanguang"},
{"phone":3777915532,"firstName":"Lion","lastName":"Reston","job_title":"Compensation Analyst","address":"Vilhelmina"},
{"phone":8774967254,"firstName":"Amalia","lastName":"Hawes","job_title":"Marketing Manager","address":"Kraton"},
{"phone":1222179107,"firstName":"Eleanora","lastName":"Skurm","job_title":"Registered Nurse","address":"Sceaux"},
{"phone":3777951823,"firstName":"Wendel","lastName":"Cawley","job_title":"Developer II","address":"Catabola"},
{"phone":5608211138,"firstName":"Perl","lastName":"Olden","job_title":"Tax Accountant","address":"Kula"},
{"phone":4279171826,"firstName":"Anthiathia","lastName":"Cunney","job_title":"Recruiting Manager","address":"Šid"},
{"phone":9873788196,"firstName":"Anna-diana","lastName":"Bartosinski","job_title":"Biostatistician IV","address":"Salvacion"},
{"phone":5189003619,"firstName":"Rebekah","lastName":"Leah","job_title":"Senior Cost Accountant","address":"Kikerino"},
{"phone":9029918753,"firstName":"Howie","lastName":"Franzoli","job_title":"Research Associate","address":"Kinshasa"},
{"phone":1068349901,"firstName":"Klemens","lastName":"Le Franc","job_title":"Media Manager IV","address":"Zhangdian"},
{"phone":1254006184,"firstName":"Gayle","lastName":"Gaudon","job_title":"Senior Developer","address":"Oskarshamn"},
{"phone":9370347545,"firstName":"Margo","lastName":"Cord","job_title":"Geologist IV","address":"Paya Dapur"},
{"phone":6346668250,"firstName":"Valida","lastName":"Cordero","job_title":"Web Developer III","address":"Poxi"},
{"phone":2917049664,"firstName":"Cherida","lastName":"Vatcher","job_title":"Desktop Support Technician","address":"Ponta do Sol"},
{"phone":4774078424,"firstName":"Edd","lastName":"MacLaig","job_title":"Staff Accountant IV","address":"Saint-Maur-des-Fossés"},
{"phone":1029923039,"firstName":"Jaquelyn","lastName":"Timby","job_title":"General Manager","address":"Gejiu"},
{"phone":2460408988,"firstName":"Consuela","lastName":"Seakes","job_title":"Electrical Engineer","address":"Sceaux"},
{"phone":5070806510,"firstName":"Manfred","lastName":"Shearman","job_title":"Help Desk Operator","address":"Thị Trấn Yên Cát"},
{"phone":7934738337,"firstName":"Boone","lastName":"Bantock","job_title":"Research Assistant III","address":"Bang Khon Thi"},
{"phone":9103334527,"firstName":"Jeno","lastName":"Tacey","job_title":"Structural Engineer","address":"Ambarawa"},
{"phone":6477344526,"firstName":"Danyette","lastName":"Bodocs","job_title":"Human Resources Manager","address":"Longxing"},
{"phone":9745953490,"firstName":"Nanni","lastName":"Campling","job_title":"Environmental Tech","address":"Baiyanghe"},
{"phone":7632964438,"firstName":"Angelle","lastName":"Ruthen","job_title":"Research Assistant I","address":"Nong Yasai"},
{"phone":4403146803,"firstName":"Pammy","lastName":"Ible","job_title":"Web Designer II","address":"Fengshou"},
{"phone":8717162315,"firstName":"Correna","lastName":"Rainforth","job_title":"Design Engineer","address":"Qihama"},
{"phone":3561477680,"firstName":"Britteny","lastName":"Dougal","job_title":"Cost Accountant","address":"Volkhovskiy"},
{"phone":5031151551,"firstName":"Hinze","lastName":"Birnie","job_title":"Staff Accountant III","address":"Třebíč"},
{"phone":4457162706,"firstName":"Claire","lastName":"Crock","job_title":"Teacher","address":"Trail"},
{"phone":7367437966,"firstName":"Ynez","lastName":"Bristowe","job_title":"Professor","address":"Housuo"},
{"phone":7667433948,"firstName":"Gabriel","lastName":"Byne","job_title":"GIS Technical Architect","address":"Ta‘izz"},
{"phone":1060731152,"firstName":"Talbot","lastName":"Renahan","job_title":"Marketing Assistant","address":"Chengdong"},
{"phone":8072465153,"firstName":"Alano","lastName":"Baguley","job_title":"Statistician I","address":"Inozemtsevo"},
{"phone":4941132599,"firstName":"Sybille","lastName":"Hugett","job_title":"Assistant Manager","address":"Kadugedong"},
{"phone":7751686200,"firstName":"Quent","lastName":"Cuss","job_title":"Mechanical Systems Engineer","address":"Gapuk"},
{"phone":1172022561,"firstName":"Ralf","lastName":"Giorgetti","job_title":"Chief Design Engineer","address":"Xiaoling"},
{"phone":3254209952,"firstName":"Althea","lastName":"Streeting","job_title":"Social Worker","address":"Kostopil’"},
{"phone":9907281846,"firstName":"Tedman","lastName":"Mocker","job_title":"Teacher","address":"Malaryta"},
{"phone":1174931952,"firstName":"Joya","lastName":"Kelinge","job_title":"Nurse","address":"Ouagadougou"},
{"phone":1048688565,"firstName":"Iolanthe","lastName":"Morrant","job_title":"Engineer III","address":"Chahe"},
{"phone":5716828498,"firstName":"Neron","lastName":"Witt","job_title":"Research Associate","address":"Češinovo"},
{"phone":8110686045,"firstName":"Codie","lastName":"Janssens","job_title":"Clinical Specialist","address":"Boconó"},
{"phone":9683044624,"firstName":"Bram","lastName":"Christy","job_title":"Automation Specialist III","address":"Coasa"},
{"phone":3289316361,"firstName":"Marisa","lastName":"Ponten","job_title":"Desktop Support Technician","address":"Biga"},
{"phone":2355661494,"firstName":"Marley","lastName":"Dyster","job_title":"Senior Sales Associate","address":"Busuanga"},
{"phone":2559720786,"firstName":"Trudie","lastName":"Draycott","job_title":"Occupational Therapist","address":"Kärdla"},
{"phone":8915871386,"firstName":"Nelia","lastName":"Pauncefort","job_title":"Engineer II","address":"Angers"},
{"phone":3019687961,"firstName":"Inez","lastName":"Echelle","job_title":"VP Product Management","address":"Zhufo"},
{"phone":7657280520,"firstName":"Alysa","lastName":"Whitfield","job_title":"Programmer III","address":"Kukës"},
{"phone":4404457159,"firstName":"Kathe","lastName":"Ferraro","job_title":"Software Test Engineer IV","address":"Rennes"},
{"phone":6368037817,"firstName":"Xymenes","lastName":"Kenchington","job_title":"Quality Engineer","address":"Usa River"},
{"phone":9714346695,"firstName":"Tonia","lastName":"Mulqueen","job_title":"Registered Nurse","address":"Nigel"},
{"phone":7735061012,"firstName":"Cordie","lastName":"Turrill","job_title":"Senior Developer","address":"Winterthur"},
{"phone":5855622731,"firstName":"Herculie","lastName":"Heggman","job_title":"Nurse Practicioner","address":"Jimaguayú"},
{"phone":2457365926,"firstName":"Terri-jo","lastName":"Haug","job_title":"Director of Sales","address":"Turpo"},
{"phone":4090748506,"firstName":"Adore","lastName":"Wittke","job_title":"Paralegal","address":"Boguchar"},
{"phone":6741535507,"firstName":"Nicky","lastName":"O'Henecan","job_title":"Physical Therapy Assistant","address":"Brämhult"},
{"phone":5258641986,"firstName":"Lauri","lastName":"Linkie","job_title":"Editor","address":"Ciwidara"},
{"phone":3559641804,"firstName":"Liv","lastName":"Giovannoni","job_title":"Financial Advisor","address":"Jaen"},
{"phone":3538566754,"firstName":"Claybourne","lastName":"Iacomo","job_title":"Environmental Specialist","address":"Croissy-sur-Seine"},
{"phone":7209027875,"firstName":"Astra","lastName":"Pohl","job_title":"Financial Analyst","address":"Frankfort"},
{"phone":4864142466,"firstName":"Mateo","lastName":"Genever","job_title":"Cost Accountant","address":"Wŏnju"},
{"phone":2012419634,"firstName":"Ranique","lastName":"Presland","job_title":"VP Sales","address":"Tamano"},
{"phone":6282771229,"firstName":"Irving","lastName":"Bavridge","job_title":"Account Representative IV","address":"Banaybanay"},
{"phone":3376646696,"firstName":"Neil","lastName":"Northidge","job_title":"Project Manager","address":"Horodok"},
{"phone":1432250034,"firstName":"Hilda","lastName":"Maher","job_title":"Structural Engineer","address":"Stony Plain"},
{"phone":8693631761,"firstName":"Annalee","lastName":"Fassam","job_title":"Graphic Designer","address":"Koukkuniemi"},
{"phone":1447279964,"firstName":"Kay","lastName":"Conkay","job_title":"Professor","address":"Huaminglou"},
{"phone":6329872012,"firstName":"Rita","lastName":"Daintrey","job_title":"Analog Circuit Design manager","address":"Vimmerby"},
{"phone":5169782545,"firstName":"Ivory","lastName":"Hordell","job_title":"Assistant Professor","address":"Dadianzi"},
{"phone":8597975471,"firstName":"Jenica","lastName":"Francescotti","job_title":"Account Executive","address":"Dve Mogili"},
{"phone":5515699864,"firstName":"Chandler","lastName":"Shrawley","job_title":"Accounting Assistant IV","address":"Paulo Afonso"},
{"phone":6081707790,"firstName":"Kristan","lastName":"Swaden","job_title":"Speech Pathologist","address":"Stony Plain"},
{"phone":6346294761,"firstName":"Fabe","lastName":"Ivatt","job_title":"Marketing Assistant","address":"Crato"},
{"phone":8338751240,"firstName":"Quinn","lastName":"Scamaden","job_title":"Actuary","address":"Beselga"},
{"phone":3954824326,"firstName":"Irwinn","lastName":"Wells","job_title":"Civil Engineer","address":"Dafang"},
{"phone":3286309652,"firstName":"Gerhardine","lastName":"Hesser","job_title":"VP Product Management","address":"Plagiári"},
{"phone":3105865291,"firstName":"Bjorn","lastName":"Ankers","job_title":"Help Desk Operator","address":"Lebak"},
{"phone":7610566291,"firstName":"Danette","lastName":"Philippe","job_title":"Quality Engineer","address":"Zhihe"},
{"phone":8089922383,"firstName":"Adel","lastName":"Werny","job_title":"Civil Engineer","address":"Aroa"},
{"phone":9687811669,"firstName":"Schuyler","lastName":"Madre","job_title":"Food Chemist","address":"Huantuo"},
{"phone":5024600473,"firstName":"Benoite","lastName":"Piquard","job_title":"Health Coach II","address":"Borabue"},
{"phone":6809096264,"firstName":"Teddy","lastName":"Broadbent","job_title":"Database Administrator I","address":"Nova Pazova"},
{"phone":5181544951,"firstName":"Algernon","lastName":"Paddick","job_title":"Project Manager","address":"Bosanski Šamac"},
{"phone":3300839572,"firstName":"Bari","lastName":"Haydock","job_title":"Operator","address":"Nijmegen"},
{"phone":2896237874,"firstName":"Juanita","lastName":"Hayne","job_title":"Registered Nurse","address":"Fonte Boa"},
{"phone":4826535968,"firstName":"Charity","lastName":"Tewelson","job_title":"Internal Auditor","address":"Hisings Kärra"},
{"phone":7974261482,"firstName":"Katrinka","lastName":"Sallowaye","job_title":"Software Test Engineer IV","address":"Krasnokuts’k"},
{"phone":4538566939,"firstName":"Padraic","lastName":"Cargill","job_title":"Engineer II","address":"Galapa"},
{"phone":4669481163,"firstName":"Camellia","lastName":"Phillott","job_title":"Analog Circuit Design manager","address":"Shuidong"},
{"phone":7888977354,"firstName":"Stephenie","lastName":"Marzelli","job_title":"Systems Administrator IV","address":"Caculé"},
{"phone":4965240059,"firstName":"Jard","lastName":"Escofier","job_title":"VP Product Management","address":"Vysotskoye"},
{"phone":8363447739,"firstName":"Jasmina","lastName":"Flament","job_title":"Geological Engineer","address":"Aghada"},
{"phone":9429504486,"firstName":"Rickert","lastName":"Autry","job_title":"Paralegal","address":"Lille"},
{"phone":9895352511,"firstName":"Marlo","lastName":"Geggus","job_title":"Health Coach II","address":"Al Muwayh"},
{"phone":1327451789,"firstName":"Matthias","lastName":"Dackombe","job_title":"Product Engineer","address":"Mahdia"},
{"phone":5512105050,"firstName":"Jameson","lastName":"Devote","job_title":"Cost Accountant","address":"Kayu Agung"},
{"phone":5589511562,"firstName":"Dulcy","lastName":"Daly","job_title":"Cost Accountant","address":"Yeping"},
{"phone":9102801689,"firstName":"Patrick","lastName":"Meiner","job_title":"Community Outreach Specialist","address":"Passo Fundo"},
{"phone":4349126008,"firstName":"Xaviera","lastName":"Shearwood","job_title":"GIS Technical Architect","address":"San Jose del Monte"},
{"phone":6720357403,"firstName":"Jessee","lastName":"Gumm","job_title":"Staff Scientist","address":"Gaoqiao"},
{"phone":3281697172,"firstName":"Marc","lastName":"Tomblings","job_title":"Data Coordiator","address":"Taochuan"},
{"phone":6999340945,"firstName":"Fara","lastName":"Bertomieu","job_title":"Occupational Therapist","address":"Ichuña"},
{"phone":3038993716,"firstName":"Brose","lastName":"Niesegen","job_title":"Recruiter","address":"Yedun"},
{"phone":3976724486,"firstName":"Maury","lastName":"Dohr","job_title":"Payment Adjustment Coordinator","address":"Szydłowo"},
{"phone":5077355609,"firstName":"Angie","lastName":"Pook","job_title":"Teacher","address":"Duyên Hải"},
{"phone":4823911015,"firstName":"Pris","lastName":"Agron","job_title":"Mechanical Systems Engineer","address":"Leeuwarden"},
{"phone":7511680439,"firstName":"Carlota","lastName":"Frowd","job_title":"Legal Assistant","address":"Ibabang Tayuman"},
{"phone":2556185243,"firstName":"Giralda","lastName":"Hawkswood","job_title":"VP Sales","address":"El Progreso"},
{"phone":1182417415,"firstName":"Stanton","lastName":"Jemmett","job_title":"Food Chemist","address":"Salt Lake City"},
{"phone":4728168394,"firstName":"Annabella","lastName":"Coots","job_title":"Marketing Manager","address":"Rennes"},
{"phone":9666232564,"firstName":"Nat","lastName":"Paddie","job_title":"Associate Professor","address":"Kachia"},
{"phone":8549112422,"firstName":"Glendon","lastName":"Lewinton","job_title":"Engineer II","address":"Peoria"},
{"phone":5652877917,"firstName":"Tommie","lastName":"Antonik","job_title":"Product Engineer","address":"Sarimukti Kaler"},
{"phone":5411524611,"firstName":"Burt","lastName":"Harnwell","job_title":"Research Assistant II","address":"Wushi"},
{"phone":7093969052,"firstName":"Ryun","lastName":"Simnett","job_title":"VP Marketing","address":"Raszowa"},
{"phone":1502036977,"firstName":"Orelia","lastName":"Corton","job_title":"Research Associate","address":"Örebro"},
{"phone":2816067825,"firstName":"Justina","lastName":"Poznan","job_title":"Research Associate","address":"Chiantla"},
{"phone":9871850628,"firstName":"Merrill","lastName":"Pinnere","job_title":"Editor","address":"Masvingo"},
{"phone":8856829476,"firstName":"Aundrea","lastName":"Markel","job_title":"Senior Quality Engineer","address":"Bukid"},
{"phone":9002143240,"firstName":"Ulrika","lastName":"Krates","job_title":"Recruiting Manager","address":"Palmira"},
{"phone":4559964025,"firstName":"Ailey","lastName":"Ausher","job_title":"Assistant Manager","address":"Zhongshan Donglu"},
{"phone":6630530125,"firstName":"Maribeth","lastName":"Calyton","job_title":"Civil Engineer","address":"Lenger"},
{"phone":7653562818,"firstName":"Tamas","lastName":"Bousquet","job_title":"Account Coordinator","address":"Miętne"},
{"phone":4937264762,"firstName":"Lyman","lastName":"Riddiford","job_title":"Chief Design Engineer","address":"Caen"},
{"phone":7681281831,"firstName":"Kerri","lastName":"Cescotti","job_title":"Nuclear Power Engineer","address":"Loureiro"},
{"phone":5738890197,"firstName":"Alexandro","lastName":"Seel","job_title":"Social Worker","address":"Gaphatshwe"},
{"phone":1934232553,"firstName":"Ham","lastName":"Como","job_title":"Assistant Manager","address":"Kefar Yona"},
{"phone":5092798450,"firstName":"Janot","lastName":"Foakes","job_title":"VP Quality Control","address":"Desa Nasol"},
{"phone":5203130140,"firstName":"Johannes","lastName":"Scartifield","job_title":"VP Quality Control","address":"Savannakhét"},
{"phone":2554956482,"firstName":"Marj","lastName":"Clunie","job_title":"Analog Circuit Design manager","address":"Wuli"},
{"phone":5246931309,"firstName":"Layney","lastName":"Dargue","job_title":"Office Assistant I","address":"Pingdu"},
{"phone":5165904672,"firstName":"Lisle","lastName":"Giovanni","job_title":"Professor","address":"Dahedian"},
{"phone":8513084603,"firstName":"Sandy","lastName":"Kerswell","job_title":"Speech Pathologist","address":"Vaxholm"},
{"phone":6697420165,"firstName":"Cissiee","lastName":"Fellgett","job_title":"Product Engineer","address":"Nyahururu"},
{"phone":6325351755,"firstName":"Chelsea","lastName":"Ardling","job_title":"Quality Control Specialist","address":"Macia"},
{"phone":2669543211,"firstName":"Rex","lastName":"Scough","job_title":"Quality Engineer","address":"Pa Tio"},
{"phone":6449114399,"firstName":"Gasparo","lastName":"Swinney","job_title":"Quality Control Specialist","address":"Fenkeng"},
{"phone":4770030858,"firstName":"Wiatt","lastName":"Panichelli","job_title":"Clinical Specialist","address":"Gostovići"},
{"phone":3253713394,"firstName":"Brandy","lastName":"Tourmell","job_title":"VP Accounting","address":"Baozhu"},
{"phone":6920404042,"firstName":"Sarine","lastName":"Assel","job_title":"Systems Administrator II","address":"Al Qāmishlī"},
{"phone":1512038321,"firstName":"Coralie","lastName":"Micheu","job_title":"Accountant IV","address":"Piraí do Sul"},
{"phone":1986145785,"firstName":"Max","lastName":"Averies","job_title":"Analyst Programmer","address":"Dongping"},
{"phone":1365780444,"firstName":"Merrill","lastName":"Kitchenside","job_title":"Legal Assistant","address":"Mersa Matruh"},
{"phone":2900469888,"firstName":"Yves","lastName":"Wince","job_title":"Sales Representative","address":"Rennes"},
{"phone":4719832794,"firstName":"Edik","lastName":"Goullee","job_title":"Senior Developer","address":"New York City"},
{"phone":9492956736,"firstName":"Clarette","lastName":"Teesdale","job_title":"Actuary","address":"Tianfu"},
{"phone":6529920041,"firstName":"Raul","lastName":"Pykerman","job_title":"Help Desk Technician","address":"Kozmice"},
{"phone":8633252667,"firstName":"Bevan","lastName":"Holston","job_title":"Actuary","address":"Santa Praxedes"},
{"phone":6505380774,"firstName":"Reamonn","lastName":"Abate","job_title":"Human Resources Manager","address":"Leles"},
{"phone":6128388923,"firstName":"Camala","lastName":"Peschmann","job_title":"Senior Quality Engineer","address":"Yilongyong"},
{"phone":6045409086,"firstName":"Lauretta","lastName":"Heyward","job_title":"Business Systems Development Analyst","address":"Kochani"},
{"phone":3793717748,"firstName":"Marita","lastName":"Menpes","job_title":"Administrative Assistant III","address":"Santa Clara"},
{"phone":1455499334,"firstName":"Nero","lastName":"Awin","job_title":"Human Resources Manager","address":"Al Bīrah"},
{"phone":9206883850,"firstName":"Gran","lastName":"Canelas","job_title":"Developer III","address":"Cikandang"},
{"phone":3507030326,"firstName":"Ardis","lastName":"Shoubridge","job_title":"Health Coach IV","address":"Salvador"},
{"phone":7238007407,"firstName":"Yehudi","lastName":"Bauman","job_title":"Legal Assistant","address":"Pueblo Nuevo"},
{"phone":1342120961,"firstName":"Robinett","lastName":"Stollenberg","job_title":"Tax Accountant","address":"Baiyang"},
{"phone":1900181420,"firstName":"Maxine","lastName":"Shires","job_title":"General Manager","address":"Galižana"},
{"phone":7629834142,"firstName":"Shanon","lastName":"Attridge","job_title":"Chief Design Engineer","address":"Barr"},
{"phone":6682372051,"firstName":"Kacey","lastName":"Vallow","job_title":"Software Engineer I","address":"Koch'ang"},
{"phone":3434401007,"firstName":"Gerrard","lastName":"Camelli","job_title":"Human Resources Assistant I","address":"Akwanga"},
{"phone":1138827138,"firstName":"Cristine","lastName":"Gotobed","job_title":"Systems Administrator I","address":"Toktogul"},
{"phone":9503440433,"firstName":"Bert","lastName":"Killgus","job_title":"VP Product Management","address":"Tojal"},
{"phone":3937267330,"firstName":"Mohammed","lastName":"Bearman","job_title":"Systems Administrator I","address":"Xiashuitou"},
{"phone":9423466854,"firstName":"Modesty","lastName":"Wingeat","job_title":"Programmer Analyst IV","address":"Hai Riêng"},
{"phone":4039154889,"firstName":"Luis","lastName":"Mungan","job_title":"Environmental Tech","address":"Jinli"},
{"phone":2873444173,"firstName":"Jude","lastName":"Redmond","job_title":"Junior Executive","address":"Oslo"},
{"phone":2571751783,"firstName":"Alia","lastName":"Penketh","job_title":"Occupational Therapist","address":"Umbanyar"},
{"phone":9262492714,"firstName":"Liv","lastName":"Guillford","job_title":"VP Accounting","address":"Volodarsk"},
{"phone":9952416894,"firstName":"Bev","lastName":"Cowing","job_title":"Quality Engineer","address":"Vereya"},
{"phone":9853024713,"firstName":"Parsifal","lastName":"Hancock","job_title":"Analog Circuit Design manager","address":"Wencheng"},
{"phone":6480682923,"firstName":"Faith","lastName":"O'Lyhane","job_title":"Project Manager","address":"Söderhamn"},
{"phone":7687934417,"firstName":"Charmain","lastName":"Filinkov","job_title":"Environmental Specialist","address":"Shumikhinskiy"},
{"phone":5488139921,"firstName":"Ebenezer","lastName":"Guislin","job_title":"VP Sales","address":"La Libertad"},
{"phone":2661620148,"firstName":"Clarence","lastName":"Vinas","job_title":"Geologist IV","address":"Rislane"},
{"phone":8450384225,"firstName":"Livvie","lastName":"Orange","job_title":"Database Administrator II","address":"Ribeirão Pires"},
{"phone":8108104562,"firstName":"Maisey","lastName":"Feast","job_title":"Staff Scientist","address":"Jingchuan"},
{"phone":4428491228,"firstName":"Evelina","lastName":"Littlefield","job_title":"Statistician IV","address":"Taounza"},
{"phone":9975340460,"firstName":"Alford","lastName":"Rapinett","job_title":"Quality Control Specialist","address":"Mozdok"},
{"phone":7398287167,"firstName":"Frederica","lastName":"O'Hoolahan","job_title":"Product Engineer","address":"Elefsína"},
{"phone":9657651609,"firstName":"Cecilla","lastName":"Coil","job_title":"Legal Assistant","address":"Khao Yoi"},
{"phone":3950446852,"firstName":"Fax","lastName":"Gammack","job_title":"Pharmacist","address":"Kuczbork-Osada"},
{"phone":8093054584,"firstName":"Loralie","lastName":"Bachanski","job_title":"Analog Circuit Design manager","address":"Xiabuji"},
{"phone":3019082857,"firstName":"Lorrie","lastName":"Hannis","job_title":"Financial Advisor","address":"Nanlü"},
{"phone":2796895123,"firstName":"Christye","lastName":"Cocklie","job_title":"Accounting Assistant II","address":"Pengbu"},
{"phone":4104442258,"firstName":"Kassie","lastName":"Cutajar","job_title":"Marketing Assistant","address":"Vale"},
{"phone":8285357998,"firstName":"Aloysius","lastName":"De Vaan","job_title":"Legal Assistant","address":"Erlangkou"},
{"phone":9987990462,"firstName":"Carlie","lastName":"Ivamy","job_title":"VP Quality Control","address":"Bafang"},
{"phone":4972268750,"firstName":"Norton","lastName":"Pariso","job_title":"Mechanical Systems Engineer","address":"Faisalābād"},
{"phone":5486328578,"firstName":"Stinky","lastName":"Backhurst","job_title":"Speech Pathologist","address":"Selajambe Satu"},
{"phone":7358355486,"firstName":"Jaclin","lastName":"Thursfield","job_title":"Geologist II","address":"Łyse"},
{"phone":4007937285,"firstName":"Deonne","lastName":"Fleming","job_title":"Programmer Analyst III","address":"Warri"},
{"phone":1066289480,"firstName":"Stu","lastName":"Lace","job_title":"Account Representative IV","address":"Araras"},
{"phone":5884239840,"firstName":"Shaughn","lastName":"Merwood","job_title":"Social Worker","address":"Sala"},
{"phone":3612513794,"firstName":"Phip","lastName":"Tunsley","job_title":"Structural Analysis Engineer","address":"Nantes"},
{"phone":5925110173,"firstName":"Reine","lastName":"Bhatia","job_title":"Help Desk Operator","address":"Outeiro"},
{"phone":8814993023,"firstName":"Martelle","lastName":"Dourin","job_title":"Financial Analyst","address":"Garisul"},
{"phone":7978176601,"firstName":"Adriane","lastName":"Rubica","job_title":"Staff Accountant III","address":"Dhali"},
{"phone":1463533790,"firstName":"Lowrance","lastName":"Moreland","job_title":"VP Product Management","address":"As Samawah"},
{"phone":6326028600,"firstName":"Eadie","lastName":"Mitroshinov","job_title":"Pharmacist","address":"Mburukullu"},
{"phone":3067107981,"firstName":"Aile","lastName":"Bafford","job_title":"Chemical Engineer","address":"Kalmar"},
{"phone":7362656196,"firstName":"Aldous","lastName":"Ladon","job_title":"Electrical Engineer","address":"Ulricehamn"},
{"phone":9738381882,"firstName":"Malory","lastName":"Brandolini","job_title":"Dental Hygienist","address":"Kalino"},
{"phone":8455869018,"firstName":"Othilia","lastName":"Dowdeswell","job_title":"Junior Executive","address":"Guanba"},
{"phone":7715874506,"firstName":"Estel","lastName":"Cleynman","job_title":"VP Accounting","address":"Santiago de los Caballeros"},
{"phone":5092329003,"firstName":"Gale","lastName":"Huggett","job_title":"Systems Administrator III","address":"Springfield"},
{"phone":5219566238,"firstName":"Nara","lastName":"Spooner","job_title":"Health Coach IV","address":"Kista"},
{"phone":9843150308,"firstName":"Homer","lastName":"Schooling","job_title":"Data Coordiator","address":"Ojrzeń"},
{"phone":6169936709,"firstName":"Jamill","lastName":"Formigli","job_title":"Director of Sales","address":"Anyu"},
{"phone":3589154688,"firstName":"Karney","lastName":"Olver","job_title":"Physical Therapy Assistant","address":"Miaotou"},
{"phone":7064520873,"firstName":"Issy","lastName":"Tudor","job_title":"Web Developer II","address":"Emiliano Zapata"},
{"phone":6240478331,"firstName":"Hayyim","lastName":"Meddick","job_title":"Junior Executive","address":"Nereta"},
{"phone":4998509303,"firstName":"Gare","lastName":"Espinoza","job_title":"Accountant IV","address":"18 de Marzo"},
{"phone":6196739469,"firstName":"Kassia","lastName":"Bertouloume","job_title":"Recruiter","address":"Gendiwu"},
{"phone":7181853576,"firstName":"Ollie","lastName":"Gierardi","job_title":"Clinical Specialist","address":"Yatsushiro"},
{"phone":9860569022,"firstName":"Mikol","lastName":"Joselevitch","job_title":"Research Assistant III","address":"Asímion"},
{"phone":4415255080,"firstName":"Whit","lastName":"Pedlar","job_title":"Software Test Engineer III","address":"Karangkeng"},
{"phone":2879310856,"firstName":"Mohammed","lastName":"Titchard","job_title":"Cost Accountant","address":"Ituverava"},
{"phone":4579199413,"firstName":"Kari","lastName":"Haldane","job_title":"Clinical Specialist","address":"El Cubolero"},
{"phone":8714995533,"firstName":"Theodor","lastName":"Waud","job_title":"Programmer II","address":"Pinheiro Machado"},
{"phone":3606871770,"firstName":"Cash","lastName":"Manketell","job_title":"Chief Design Engineer","address":"Nîmes"},
{"phone":9606140548,"firstName":"Odelle","lastName":"Slaght","job_title":"Software Engineer III","address":"Primorskiy"},
{"phone":6612391982,"firstName":"Vin","lastName":"Marde","job_title":"Financial Analyst","address":"Inkerman"},
{"phone":7648645742,"firstName":"Eberhard","lastName":"Wehner","job_title":"Senior Editor","address":"Novo Hamburgo"},
{"phone":4123052121,"firstName":"Rayna","lastName":"Zielinski","job_title":"Budget/Accounting Analyst IV","address":"Liancheng"},
{"phone":9460010460,"firstName":"Law","lastName":"Ferrers","job_title":"Accountant I","address":"Shapa"},
{"phone":2755961894,"firstName":"Suzi","lastName":"Barsam","job_title":"Teacher","address":"Minchinābād"},
{"phone":5258906957,"firstName":"Nevil","lastName":"Staig","job_title":"Geologist IV","address":"Pentéli"},
{"phone":3102257292,"firstName":"Patten","lastName":"Raulston","job_title":"Project Manager","address":"Gaolong"},
{"phone":9143248351,"firstName":"Maris","lastName":"Dungay","job_title":"Desktop Support Technician","address":"Castrovirreyna"},
{"phone":4815180860,"firstName":"Thornton","lastName":"Charker","job_title":"Account Executive","address":"José de Freitas"},
{"phone":3803233497,"firstName":"Karna","lastName":"Witcombe","job_title":"Pharmacist","address":"Teberda"},
{"phone":4883949585,"firstName":"Basil","lastName":"MacFadzean","job_title":"Programmer Analyst I","address":"Riangwale"},
{"phone":3710725534,"firstName":"Madelin","lastName":"Kilrow","job_title":"Computer Systems Analyst IV","address":"Sionogan"},
{"phone":9969108703,"firstName":"Normand","lastName":"Marquot","job_title":"Computer Systems Analyst I","address":"Gaspra"},
{"phone":7036487953,"firstName":"Erroll","lastName":"Shilliday","job_title":"Geological Engineer","address":"Gavarr"},
{"phone":6298802194,"firstName":"Sibel","lastName":"Skerman","job_title":"Senior Sales Associate","address":"Maria Aurora"},
{"phone":4271797201,"firstName":"Rufus","lastName":"Wollen","job_title":"Speech Pathologist","address":"Kap Choeng"},
{"phone":6168312522,"firstName":"Salvidor","lastName":"Balke","job_title":"Programmer IV","address":"Gombe"},
{"phone":4071737342,"firstName":"Fritz","lastName":"Bergstram","job_title":"Nurse","address":"Kardítsa"},
{"phone":9976804448,"firstName":"Stanfield","lastName":"Outibridge","job_title":"Business Systems Development Analyst","address":"Balesari"},
{"phone":2464790220,"firstName":"Liane","lastName":"Greder","job_title":"Executive Secretary","address":"Tiling"},
{"phone":3453288902,"firstName":"Thedrick","lastName":"Bonar","job_title":"Senior Developer","address":"Hekou"},
{"phone":6036292754,"firstName":"Juditha","lastName":"Ellerker","job_title":"VP Marketing","address":"São Domingos"},
{"phone":9835625736,"firstName":"Gerry","lastName":"Tappin","job_title":"Cost Accountant","address":"Caen"},
{"phone":9527300582,"firstName":"Caryn","lastName":"Lapsley","job_title":"General Manager","address":"Kurmanayevka"},
{"phone":5564674544,"firstName":"Joni","lastName":"Habershon","job_title":"Registered Nurse","address":"Stockton"},
{"phone":3868276598,"firstName":"Erna","lastName":"Cossons","job_title":"Quality Control Specialist","address":"Manonjaya"},
{"phone":1301498073,"firstName":"Hartley","lastName":"Eccleston","job_title":"Research Nurse","address":"Jixi"},
{"phone":9670090136,"firstName":"Zelma","lastName":"Maple","job_title":"Accountant I","address":"Bërxull"},
{"phone":7392508822,"firstName":"Mace","lastName":"Laviste","job_title":"Senior Developer","address":"Hoktember"},
{"phone":5415963930,"firstName":"Dallis","lastName":"Berrygun","job_title":"Human Resources Assistant II","address":"Kesheng"},
{"phone":9083334967,"firstName":"Linnell","lastName":"Andre","job_title":"Tax Accountant","address":"Eskilstuna"},
{"phone":7328483801,"firstName":"Wildon","lastName":"Croft","job_title":"Recruiting Manager","address":"Huangtan"},
{"phone":7540634481,"firstName":"Irving","lastName":"Rowena","job_title":"Financial Analyst","address":"Haduohe"},
{"phone":7546325029,"firstName":"Cassandry","lastName":"Bambrugh","job_title":"Programmer Analyst II","address":"Colombes"},
{"phone":6240050842,"firstName":"Kanya","lastName":"Mocher","job_title":"Paralegal","address":"Yanggu"},
{"phone":8926113791,"firstName":"Lenora","lastName":"Charlon","job_title":"Sales Representative","address":"São Paio de Seide"},
{"phone":7381188582,"firstName":"Philipa","lastName":"Brandrick","job_title":"Nuclear Power Engineer","address":"Pregradnaya"},
{"phone":8593615054,"firstName":"Mano","lastName":"Brumby","job_title":"Programmer Analyst I","address":"Karengan"},
{"phone":8482897508,"firstName":"Bliss","lastName":"Logie","job_title":"Assistant Professor","address":"Yanahuaya"},
{"phone":3596359857,"firstName":"Howard","lastName":"Sainz","job_title":"VP Marketing","address":"Camiri"},
{"phone":9092898117,"firstName":"Hubey","lastName":"Marris","job_title":"Senior Sales Associate","address":"Luci"},
{"phone":7456993892,"firstName":"Chrotoem","lastName":"Sporrij","job_title":"Budget/Accounting Analyst II","address":"Reconquista"},
{"phone":8367556474,"firstName":"Leonelle","lastName":"Stallworthy","job_title":"Health Coach IV","address":"Gesing"},
{"phone":8087216327,"firstName":"Bernarr","lastName":"Dobkin","job_title":"Tax Accountant","address":"Pandat"},
{"phone":1185676311,"firstName":"Cele","lastName":"Maryin","job_title":"Librarian","address":"Khvastovichi"},
{"phone":5172336291,"firstName":"Holli","lastName":"Punchard","job_title":"Recruiting Manager","address":"Dolgoprudnyy"},
{"phone":3829517750,"firstName":"Eleni","lastName":"Counihan","job_title":"Pharmacist","address":"Xamba"},
{"phone":5599387915,"firstName":"Ryan","lastName":"Knott","job_title":"Social Worker","address":"Tyret’ Pervaya"},
{"phone":8214244841,"firstName":"Godfrey","lastName":"Normanvill","job_title":"Editor","address":"Chongmin"},
{"phone":7177268543,"firstName":"Cariotta","lastName":"Veracruysse","job_title":"Speech Pathologist","address":"Yejia"},
{"phone":7210007290,"firstName":"Solly","lastName":"Sperry","job_title":"Structural Engineer","address":"Gaotian"},
{"phone":4020118782,"firstName":"Cherie","lastName":"Hairsnape","job_title":"Geologist I","address":"Beima"},
{"phone":8927790150,"firstName":"Skell","lastName":"Say","job_title":"Professor","address":"Evansville"},
{"phone":6859750784,"firstName":"Hillard","lastName":"Pinchon","job_title":"Librarian","address":"Brignoles"},
{"phone":4528259139,"firstName":"Beck","lastName":"Rothera","job_title":"Payment Adjustment Coordinator","address":"Jambangan"},
{"phone":2119893476,"firstName":"Johnny","lastName":"Broxap","job_title":"Structural Engineer","address":"Jaraguá"},
{"phone":9899031196,"firstName":"Ilario","lastName":"Concannon","job_title":"Research Nurse","address":"Andir"},
{"phone":7619421877,"firstName":"Margeaux","lastName":"Cooley","job_title":"Administrative Officer","address":"Qingshui"},
{"phone":9229210570,"firstName":"Crissie","lastName":"Yarr","job_title":"Sales Representative","address":"Ukata"},
{"phone":5178397997,"firstName":"Pincus","lastName":"Girardot","job_title":"Director of Sales","address":"San Fernando de Monte Cristi"},
{"phone":5558029133,"firstName":"Calv","lastName":"Lattimore","job_title":"Mechanical Systems Engineer","address":"Strabychovo"},
{"phone":5358876447,"firstName":"Domenico","lastName":"Balsellie","job_title":"Professor","address":"Bang Pa-in"},
{"phone":3585374884,"firstName":"Alley","lastName":"Bruntjen","job_title":"Mechanical Systems Engineer","address":"Ipoh"},
{"phone":4450241536,"firstName":"Sherrie","lastName":"Sly","job_title":"Developer III","address":"San Agustin"},
{"phone":4765443806,"firstName":"Cory","lastName":"Albisser","job_title":"Junior Executive","address":"Arrën"},
{"phone":8025307121,"firstName":"Dre","lastName":"Mounter","job_title":"Research Assistant II","address":"Jincheng"},
{"phone":6836178814,"firstName":"Chaunce","lastName":"Levane","job_title":"Internal Auditor","address":"Panjerrejo"},
{"phone":2888595668,"firstName":"West","lastName":"Yeell","job_title":"Software Engineer II","address":"Renfrew"},
{"phone":3207351853,"firstName":"Roarke","lastName":"Kliement","job_title":"Administrative Assistant II","address":"Kiltamagh"},
{"phone":3202305335,"firstName":"Ardith","lastName":"Pedwell","job_title":"Teacher","address":"Trindade"},
{"phone":9351711014,"firstName":"Barbara-anne","lastName":"Dulin","job_title":"Analog Circuit Design manager","address":"Raoshi"},
{"phone":8108776614,"firstName":"Kendricks","lastName":"Flounders","job_title":"Programmer Analyst III","address":"Lingtou"},
{"phone":6955338713,"firstName":"Vergil","lastName":"Zannini","job_title":"Internal Auditor","address":"Mixco"},
{"phone":9720818866,"firstName":"Brook","lastName":"Birkmyr","job_title":"Data Coordiator","address":"San Clemente"},
{"phone":3776866919,"firstName":"Rolland","lastName":"Duce","job_title":"Recruiting Manager","address":"Shuanghe"},
{"phone":4216966659,"firstName":"Isac","lastName":"Grasha","job_title":"Computer Systems Analyst I","address":"Pécs"},
{"phone":6743075618,"firstName":"Crin","lastName":"MacPaike","job_title":"Staff Accountant III","address":"Huambo"},
{"phone":5647565394,"firstName":"Hester","lastName":"Northwood","job_title":"Project Manager","address":"Bratislava"},
{"phone":2204194460,"firstName":"Eleanora","lastName":"Henrique","job_title":"Senior Developer","address":"Bayuwan"},
{"phone":2052123655,"firstName":"Clo","lastName":"Lane","job_title":"Assistant Media Planner","address":"Buzuluk"},
{"phone":5392613246,"firstName":"Janeczka","lastName":"Simnett","job_title":"Senior Developer","address":"Tyrawa Wołoska"},
{"phone":5530700824,"firstName":"Kaspar","lastName":"Laurenz","job_title":"Automation Specialist I","address":"Sundawenang"},
{"phone":6368815018,"firstName":"Abbott","lastName":"Gooders","job_title":"Media Manager II","address":"Hotsk"},
{"phone":6233572482,"firstName":"Homerus","lastName":"Andrag","job_title":"Research Associate","address":"Xingyi"},
{"phone":4045706053,"firstName":"Lothario","lastName":"Martinelli","job_title":"Director of Sales","address":"Nelson"},
{"phone":5089684116,"firstName":"Rurik","lastName":"Retchless","job_title":"Food Chemist","address":"Caucaia"},
{"phone":1669277867,"firstName":"Fredi","lastName":"Revans","job_title":"Automation Specialist IV","address":"North Shore"},
{"phone":2505682030,"firstName":"Calv","lastName":"Sterrick","job_title":"Chemical Engineer","address":"Donskoy"},
{"phone":6276909164,"firstName":"Sylvan","lastName":"Frame","job_title":"Recruiter","address":"Tagum"},
{"phone":2577616580,"firstName":"Darcy","lastName":"Brokenshaw","job_title":"Media Manager III","address":"Cinunjang"},
{"phone":5423231674,"firstName":"Erasmus","lastName":"Vida","job_title":"Developer IV","address":"Al Maḩfid"},
{"phone":2853329899,"firstName":"Gan","lastName":"Dory","job_title":"Accounting Assistant I","address":"Lambayong"},
{"phone":1835895964,"firstName":"Douglass","lastName":"Poyzer","job_title":"Health Coach IV","address":"Shebekino"},
{"phone":5325359620,"firstName":"Shem","lastName":"Kiljan","job_title":"Mechanical Systems Engineer","address":"Chenyangzhai"},
{"phone":8731353020,"firstName":"Jaquith","lastName":"Shreenan","job_title":"Recruiting Manager","address":"Vayk’"},
{"phone":8589916716,"firstName":"Rodolph","lastName":"Belliard","job_title":"Account Coordinator","address":"Bajo"},
{"phone":5178992403,"firstName":"Sherline","lastName":"Waldocke","job_title":"Design Engineer","address":"Lamawalang"},
{"phone":4080922380,"firstName":"Jacky","lastName":"Ryde","job_title":"Internal Auditor","address":"Castelo"},
{"phone":3633657375,"firstName":"Tabbie","lastName":"Noriega","job_title":"Product Engineer","address":"Cherbourg-Octeville"},
{"phone":5982934655,"firstName":"Jolee","lastName":"Boxen","job_title":"Senior Cost Accountant","address":"Yanji"},
{"phone":6379222769,"firstName":"Patten","lastName":"Birkett","job_title":"Nurse Practicioner","address":"Pentre"},
{"phone":6071580142,"firstName":"Chickie","lastName":"Wyllcock","job_title":"VP Sales","address":"Andovoranto"},
{"phone":7503841028,"firstName":"Rebecca","lastName":"Doody","job_title":"Biostatistician II","address":"Struga"},
{"phone":9229376093,"firstName":"Fanchon","lastName":"Sillett","job_title":"Registered Nurse","address":"Gubukjero Timuk"},
{"phone":7738030271,"firstName":"Hayward","lastName":"Testin","job_title":"Project Manager","address":"Yuzhou"},
{"phone":1976735889,"firstName":"Corenda","lastName":"Morcom","job_title":"Social Worker","address":"Singajaya"},
{"phone":1179577116,"firstName":"Clint","lastName":"Remer","job_title":"Internal Auditor","address":"Gavião"},
{"phone":6240823123,"firstName":"Janeen","lastName":"Thurske","job_title":"Environmental Tech","address":"Xiancun"},
{"phone":9833623838,"firstName":"Sukey","lastName":"Pinilla","job_title":"Speech Pathologist","address":"Porkhov"},
{"phone":2926487518,"firstName":"Belle","lastName":"Mayman","job_title":"Senior Editor","address":"Chase"},
{"phone":8420003260,"firstName":"Sibel","lastName":"Van den Velden","job_title":"Paralegal","address":"Penghu"},
{"phone":5321934949,"firstName":"Douglass","lastName":"Gerrels","job_title":"Research Assistant IV","address":"Shatian"},
{"phone":8597486719,"firstName":"Candie","lastName":"Jackett","job_title":"Civil Engineer","address":"Agdangan"},
{"phone":9972634343,"firstName":"Cart","lastName":"Merington","job_title":"Human Resources Assistant I","address":"Tha Muang"},
{"phone":4230544050,"firstName":"Elvis","lastName":"Chinnery","job_title":"Staff Scientist","address":"Apaga"},
{"phone":5548707800,"firstName":"Stephenie","lastName":"Spark","job_title":"Geological Engineer","address":"Serzedo"},
{"phone":3845735089,"firstName":"Elton","lastName":"Monger","job_title":"Human Resources Assistant I","address":"Sumbersewu"},
{"phone":7468444103,"firstName":"Jehanna","lastName":"Ramas","job_title":"VP Quality Control","address":"Nggambel"},
{"phone":2450985419,"firstName":"Raff","lastName":"Dewbury","job_title":"General Manager","address":"Xin’an"},
{"phone":3412955833,"firstName":"Sollie","lastName":"Hourston","job_title":"Human Resources Manager","address":"Yantai"},
{"phone":6106588819,"firstName":"Rosmunda","lastName":"Smeall","job_title":"Help Desk Operator","address":"Banjar Dukuh"},
{"phone":3046511702,"firstName":"Lewiss","lastName":"Burgill","job_title":"Speech Pathologist","address":"Nianyushan"},
{"phone":9756941619,"firstName":"Carrissa","lastName":"Gever","job_title":"General Manager","address":"Tignoan"},
{"phone":5401531093,"firstName":"Stillmann","lastName":"Belchamp","job_title":"Computer Systems Analyst IV","address":"Shagedu"},
{"phone":4281785000,"firstName":"Garald","lastName":"Safe","job_title":"Professor","address":"Frydrychowice"},
{"phone":2335587591,"firstName":"Gillie","lastName":"O'Dowd","job_title":"Mechanical Systems Engineer","address":"Ngô Đồng"},
{"phone":4189065964,"firstName":"Kevyn","lastName":"Beilby","job_title":"Senior Editor","address":"Fontenay-sous-Bois"},
{"phone":9224516056,"firstName":"Anette","lastName":"McCahey","job_title":"Sales Associate","address":"Shchūchīnsk"},
{"phone":3995575349,"firstName":"Coreen","lastName":"Reedman","job_title":"Marketing Assistant","address":"Novhorod-Sivers’kyy"},
{"phone":4038219480,"firstName":"Layney","lastName":"Petschelt","job_title":"Quality Engineer","address":"Panite"},
{"phone":8872592707,"firstName":"Sky","lastName":"Habert","job_title":"Administrative Assistant I","address":"Miguel Pereira"},
{"phone":9182573920,"firstName":"Cindra","lastName":"Houlton","job_title":"Statistician IV","address":"Morelos"},
{"phone":5562189873,"firstName":"Nikolai","lastName":"Knoles","job_title":"Administrative Officer","address":"Molepolole"},
{"phone":6189959499,"firstName":"Hollyanne","lastName":"Munden","job_title":"Financial Analyst","address":"Pigcawayan"},
{"phone":6578327794,"firstName":"Glynda","lastName":"Tagg","job_title":"Registered Nurse","address":"Rokietnica"},
{"phone":1938860556,"firstName":"Delmor","lastName":"Dehm","job_title":"Senior Editor","address":"Sankeng"},
{"phone":5860744204,"firstName":"Lula","lastName":"Goulding","job_title":"Community Outreach Specialist","address":"Batutua"},
{"phone":1861979602,"firstName":"Abba","lastName":"Howel","job_title":"Environmental Tech","address":"Kigoma"},
{"phone":4338722014,"firstName":"Giorgia","lastName":"Vina","job_title":"Software Engineer IV","address":"Quinta da Torre"},
{"phone":2486691291,"firstName":"Kienan","lastName":"Lanktree","job_title":"Cost Accountant","address":"Kassala"},
{"phone":2543337921,"firstName":"Sibelle","lastName":"Hopfer","job_title":"Senior Quality Engineer","address":"Mandiana"},
{"phone":9266557572,"firstName":"Nell","lastName":"McColley","job_title":"Accounting Assistant IV","address":"Wupu"},
{"phone":4659904812,"firstName":"Celle","lastName":"Sunman","job_title":"Food Chemist","address":"Sant Julià de Lòria"},
{"phone":1864480505,"firstName":"Tamara","lastName":"Wilcinskis","job_title":"Research Associate","address":"Loudi"},
{"phone":5261502817,"firstName":"Wright","lastName":"Dungay","job_title":"Internal Auditor","address":"Mesa"},
{"phone":2836489725,"firstName":"Chelsey","lastName":"Unworth","job_title":"Staff Accountant II","address":"Konibodom"},
{"phone":8335938447,"firstName":"Lyndsie","lastName":"Gershom","job_title":"Accountant I","address":"Valsamáta"},
{"phone":6432190985,"firstName":"Vic","lastName":"Coffelt","job_title":"Human Resources Assistant IV","address":"Lyaskelya"},
{"phone":3786779696,"firstName":"Gael","lastName":"Struis","job_title":"Senior Financial Analyst","address":"Chahe"},
{"phone":5937380362,"firstName":"Sylvester","lastName":"Raigatt","job_title":"VP Marketing","address":"Shubenka"},
{"phone":5980245425,"firstName":"Dreddy","lastName":"Elvey","job_title":"Media Manager IV","address":"Yangchao"},
{"phone":2737422198,"firstName":"Ewan","lastName":"Cuddy","job_title":"Staff Scientist","address":"Jetis"},
{"phone":7941097333,"firstName":"Lindy","lastName":"Minnis","job_title":"Design Engineer","address":"Damietta"},
{"phone":4193296904,"firstName":"Spenser","lastName":"Gorioli","job_title":"Teacher","address":"Lincheng"},
{"phone":4122263184,"firstName":"Kerrin","lastName":"Farra","job_title":"Analog Circuit Design manager","address":"Ningxi"},
{"phone":6198010610,"firstName":"Tana","lastName":"Castro","job_title":"Office Assistant II","address":"Granja do Tedo"},
{"phone":2763502917,"firstName":"Amerigo","lastName":"Rance","job_title":"Software Engineer II","address":"Štitar"},
{"phone":2464046397,"firstName":"Robbert","lastName":"Fouldes","job_title":"Administrative Officer","address":"Tilburg"},
{"phone":6072852694,"firstName":"Frederich","lastName":"Woodings","job_title":"Recruiter","address":"Longsha"},
{"phone":9712271302,"firstName":"Donaugh","lastName":"Squibb","job_title":"Senior Developer","address":"IJmuiden"},
{"phone":1980183957,"firstName":"Jaclin","lastName":"Alpine","job_title":"Community Outreach Specialist","address":"Huangcun"},
{"phone":2859084892,"firstName":"Catina","lastName":"Pick","job_title":"Help Desk Operator","address":"Colares"},
{"phone":7751985256,"firstName":"Barr","lastName":"Kale","job_title":"Senior Cost Accountant","address":"Rajhrad"},
{"phone":7623810112,"firstName":"Olga","lastName":"Lawson","job_title":"Business Systems Development Analyst","address":"Amirdzhan"},
{"phone":6680951936,"firstName":"Rubin","lastName":"Jewitt","job_title":"Executive Secretary","address":"Valdice"},
{"phone":7123984500,"firstName":"Flynn","lastName":"Gally","job_title":"Geologist II","address":"Monastyryshche"},
{"phone":4790336290,"firstName":"Denney","lastName":"Wigmore","job_title":"Account Representative I","address":"Duwakkandung"},
{"phone":2096806432,"firstName":"Kayla","lastName":"Venard","job_title":"Actuary","address":"Kulautuva"},
{"phone":5017303613,"firstName":"Torey","lastName":"Biesinger","job_title":"Developer IV","address":"Mogi das Cruzes"},
{"phone":9072333185,"firstName":"Veronika","lastName":"Garrioch","job_title":"Statistician IV","address":"Borūjerd"},
{"phone":5368888561,"firstName":"Tedd","lastName":"Gooley","job_title":"Product Engineer","address":"Palon"},
{"phone":4928715409,"firstName":"Claudine","lastName":"McAree","job_title":"Budget/Accounting Analyst I","address":"Kolobolon"},
{"phone":7605959209,"firstName":"Muffin","lastName":"Grishechkin","job_title":"Recruiter","address":"Koffiefontein"},
{"phone":5954659043,"firstName":"Alexine","lastName":"Methven","job_title":"Research Nurse","address":"Tayasan"},
{"phone":8340764132,"firstName":"Nolana","lastName":"Iddenden","job_title":"Mechanical Systems Engineer","address":"Hulan"},
{"phone":4804826181,"firstName":"Benito","lastName":"Craik","job_title":"Financial Analyst","address":"München"},
{"phone":4736636151,"firstName":"Cherida","lastName":"Jane","job_title":"Payment Adjustment Coordinator","address":"Górki Wielkie"},
{"phone":5285529392,"firstName":"Lisha","lastName":"Pennyman","job_title":"Occupational Therapist","address":"Al Munīrah"},
{"phone":4096568598,"firstName":"Hailee","lastName":"Hairsine","job_title":"Biostatistician III","address":"Boulder"},
{"phone":8180967945,"firstName":"Kelsey","lastName":"Busswell","job_title":"Librarian","address":"Macapsing"},
{"phone":3396647688,"firstName":"Brendin","lastName":"Beddoes","job_title":"Graphic Designer","address":"Albertville"},
{"phone":8074260716,"firstName":"Vittoria","lastName":"Liversidge","job_title":"Computer Systems Analyst IV","address":"Shanghu"},
{"phone":4739006420,"firstName":"Kelsy","lastName":"Bende","job_title":"Human Resources Manager","address":"Pining"},
{"phone":1960217135,"firstName":"Nani","lastName":"Connal","job_title":"Sales Representative","address":"Cana Chapetón"},
{"phone":1322403760,"firstName":"Derk","lastName":"Proppers","job_title":"Social Worker","address":"Sigou"},
{"phone":9276677393,"firstName":"Towny","lastName":"Chippindale","job_title":"Media Manager II","address":"Lipsko"},
{"phone":5092395256,"firstName":"Ruperto","lastName":"Wanstall","job_title":"Engineer I","address":"Mouhijärvi"},
{"phone":4639752771,"firstName":"Chiquia","lastName":"Caren","job_title":"Project Manager","address":"Aguelmous"}]